{
  "id": "millieFujimoriJäähammasArklightHlaar",
  "path": "Millie,Fujimori_Jäähammas_Arklight_Hlaar",
  "name": "Millie Fujimori Hlaar",
  "fullName": "Millie Fujimori Jäähammas Arklight Hlaar",
  "firstName": [
    "Millie"
  ],
  "lastName": [
    "Fujimori",
    "Jäähammas",
    "Arklight",
    "Hlaar"
  ],
  "data": {
    "orientation": "orientation",
    "gender": "gender",
    "age": "age",
    "race": "race"
  },
  "appearance": {
    "skin": "skin",
    "text": "text",
    "height": "height",
    "hair": "hair",
    "weight": "weight",
    "eyes": "eyes"
  },
  "bio": "text"
}
